{
    "name": "LaTeX Codespace Template",
    "dockerComposeFile": ["docker-compose.yml"],
    "service": "vscode",
    "runServices": ["vscode"],
    "shutdownAction": "stopCompose",
    "workspaceFolder": "/workspace",
    "postCreateCommand": "bash /workspace/scripts/setup-hooks.sh",
    "customizations": {
        "vscode": {
            "extensions": [
                // LaTeX
                "james-yu.latex-workshop",
                // Git
                "eamodio.gitlens",
                // GitHub
                "GitHub.copilot",
                "GitHub.copilot-chat",
                "GitHub.vscode-pull-request-github",
                // Editing helpers
                "shardulm94.trailing-spaces",
                "stkb.rewrap",
                "streetsidesoftware.code-spell-checker",
                // Markdown
                "yzhang.markdown-all-in-one",
                // YAML (for config files)
                "redhat.vscode-yaml"
            ],
            "settings": {
                // ── General editor ──────────────────────────────────────
                // LaTeX Workshop / linting / spell-check / word-count settings
                // live in .vscode/settings.json (the single source of truth,
                // so Codespace and local VS Code never drift out of sync).
                "files.eol": "\n",
                "files.trimTrailingWhitespace": true,
                "files.insertFinalNewline": true,
                "editor.wordWrap": "on",
                "editor.rulers": [100],
                "editor.fontSize": 14,
                "files.autoSave": "afterDelay",
                "files.autoSaveDelay": 120000,

                // ── Spell checker ───────────────────────────────────────
                "cSpell.language": "en",
                "cSpell.enableFiletypes": ["latex", "bibtex"],

                // ── Copilot ─────────────────────────────────────────────
                "github.copilot.enable": {
                    "latex": true,
                    "markdown": true,
                    "bibtex": true,
                    "plaintext": true
                },

                // ── Word count ──────────────────────────────────────────
                "latex-utilities.countWord.path": "texcount",
                "latex-utilities.countWord.args": ["%DOCFILE%"],
                "latex-utilities.countWord.format": "${words} words total, ${wordsBody} in body",

                // ── Formatting on save ──────────────────────────────────
                "editor.formatOnSave": true
            }
        }
    }
}
